pavpy/Tycho_BV_Bessel2000.dat
pavpy/__init__.py
pavpy/models.py
pavpy/pavol1l2.py
pavpy/stagger_4term_coeffs.json
pavpy/tel_locations.txt
pavpy/utils.py
pavpy-0.1.2.dist-info/LICENSE
pavpy-0.1.2.dist-info/WHEEL
pavpy-0.1.2.dist-info/METADATA
pavpy-0.1.2.dist-info/RECORD
